calcdemo/__init__.py
sahithcalc-0.1.1.dist-info/LICENSE.txt
sahithcalc-0.1.1.dist-info/METADATA
sahithcalc-0.1.1.dist-info/WHEEL
sahithcalc-0.1.1.dist-info/top_level.txt
sahithcalc-0.1.1.dist-info/RECORD
