Metadata-Version: 2.1
Name: sahithcalc
Version: 0.1.1
Summary: Basic calculator
Home-page: UNKNOWN
Author: Sahith
Author-email: sahith.varma.03@gmail.com
License: UNKNOWN
Platform: UNKNOWN
Classifier: Programming Language :: Python :: 3
Classifier: License :: OSI Approved :: MIT License
Classifier: Operating System :: OS Independent
License-File: LICENSE.txt
